csv_json_converter_mtba/__init__.py
csv_json_converter_mtba/converter.py
csv_json_converter_mtba-0.1.4.dist-info/entry_points.txt
csv_json_converter_mtba-0.1.4.dist-info/WHEEL
csv_json_converter_mtba-0.1.4.dist-info/METADATA
csv_json_converter_mtba-0.1.4.dist-info/RECORD
