Metadata-Version: 2.1
Name: csv-json-converter-mtba
Version: 0.1.4
Summary: Conversor CSV-JSON
Author: Marco Andrade
Author-email: marcotbandrade@gmail.com
Requires-Python: >=3.10,<4.0
Classifier: Programming Language :: Python :: 3
Classifier: Programming Language :: Python :: 3.10
Requires-Dist: click (>=8.0.3,<9.0.0)
